qik/__init__.py
qik/arch.py
qik/cache.py
qik/cli.py
qik/cmd.py
qik/conf.py
qik/console.py
qik/ctx.py
qik/dep.py
qik/errors.py
qik/file.py
qik/func.py
qik/hash.py
qik/lazy.py
qik/logger.py
qik/merge.sh
qik/py.typed
qik/pygraph/__init__.py
qik/pygraph/cmd.py
qik/pygraph/conf.py
qik/pygraph/core.py
qik/pygraph/dep.py
qik/pygraph/qik.toml
qik/pygraph/qikplugin.py
qik/pygraph/utils.py
qik/runnable.py
qik/runner.py
qik/s3/__init__.py
qik/s3/cache.py
qik/s3/qikplugin.py
qik/shell.py
qik/space.py
qik/unset.py
qik/uv/__init__.py
qik/uv/cmd.py
qik/uv/conf.py
qik/uv/qik.toml
qik/uv/qikplugin.py
qik/uv/utils.py
qik/uv/venv.py
qik/venv.py
qik/version.py
qik/watcher.py
qik-0.2.8.dist-info/METADATA
qik-0.2.8.dist-info/WHEEL
qik-0.2.8.dist-info/entry_points.txt
qik-0.2.8.dist-info/licenses/LICENSE
qik-0.2.8.dist-info/RECORD
