Metadata-Version: 2.4
Name: qik
Version: 0.2.8
Summary: Tame your monorepo. Make CI fast again.
License: BSD-3-Clause
License-File: LICENSE
Author: Wes Kendall
Requires-Python: >=3.10.0,<4
Classifier: Intended Audience :: Developers
Classifier: License :: OSI Approved :: BSD License
Classifier: Operating System :: OS Independent
Classifier: Programming Language :: Python
Classifier: Programming Language :: Python :: 3
Classifier: Programming Language :: Python :: 3.10
Classifier: Programming Language :: Python :: 3.11
Classifier: Programming Language :: Python :: 3.12
Classifier: Programming Language :: Python :: 3.13
Classifier: Programming Language :: Python :: 3.14
Classifier: Programming Language :: Python :: 3 :: Only
Provides-Extra: dev
Provides-Extra: pygraph
Provides-Extra: s3
Provides-Extra: uv
Provides-Extra: watch
Requires-Dist: boto3 (>=1) ; extra == "s3"
Requires-Dist: grimp (>=3.4.1) ; extra == "pygraph" or extra == "dev"
Requires-Dist: msgspec (>=0.19.0)
Requires-Dist: rich (>=13)
Requires-Dist: rustworkx (>=0.15.1) ; extra == "pygraph" or extra == "dev"
Requires-Dist: typing-extensions (>=4.11.0)
Requires-Dist: uv (>=0.4.18) ; extra == "uv" or extra == "dev"
Requires-Dist: watchdog (>=4) ; extra == "watch" or extra == "dev"
Requires-Dist: xxhash (>=3.4.1)
Project-URL: Documentation, https://qik.readthedocs.io
Project-URL: Homepage, https://github.com/AmbitionEng/qik
Project-URL: Repository, https://github.com/AmbitionEng/qik
